BTEdb.py
BTEdb-7.0.1.dist-info/DESCRIPTION.rst
BTEdb-7.0.1.dist-info/METADATA
BTEdb-7.0.1.dist-info/RECORD
BTEdb-7.0.1.dist-info/WHEEL
BTEdb-7.0.1.dist-info/metadata.json
BTEdb-7.0.1.dist-info/top_level.txt
