Metadata-Version: 2.0
Name: BTEdb
Version: 7.0.1
Summary: Python schemaless JSON/YAML database interface
Home-page: http://github.com/nilesr/BTEdb
Author: Peter Rogoff
Author-email: peter@rogoff.xyz
License: UNKNOWN
Platform: UNKNOWN
Requires-Dist: dill
